.DS_Store
faster_than_light/__init__.py
faster_than_light/builder.py
faster_than_light/cli.py
faster_than_light/exceptions.py
faster_than_light/gate.py
faster_than_light/inventory.py
faster_than_light/local.py
faster_than_light/message.py
faster_than_light/module.py
faster_than_light/ssh.py
faster_than_light/types.py
faster_than_light/util.py
faster_than_light/ftl_gate/__init__.py
faster_than_light/ftl_gate/__main__.py
faster_than_light-0.1.7.dist-info/AUTHORS.rst
faster_than_light-0.1.7.dist-info/LICENSE
faster_than_light-0.1.7.dist-info/METADATA
faster_than_light-0.1.7.dist-info/WHEEL
faster_than_light-0.1.7.dist-info/entry_points.txt
faster_than_light-0.1.7.dist-info/top_level.txt
faster_than_light-0.1.7.dist-info/RECORD
