Metadata-Version: 2.2
Name: faster_than_light
Version: 0.1.7
License-File: LICENSE
License-File: AUTHORS.rst
Requires-Dist: asyncssh
Requires-Dist: importlib_resources
Requires-Dist: pyyaml
Requires-Dist: docopt
Requires-Dist: click
Requires-Dist: pip
Requires-Dist: wheel
Requires-Dist: aiomultiprocess
